[
  {
    "id": 7,
    "engine": "parcels",
    "source": "opendataphilly",
    "started_at": "2026-03-10T10:48:24.892310+00:00",
    "completed_at": "2026-03-10T10:50:28.463690+00:00",
    "records_added": 0,
    "records_updated": 0,
    "status": "completed",
    "error": null
  },
  {
    "id": 6,
    "engine": "systems",
    "source": "usaspending",
    "started_at": "2026-03-10T10:47:31.725864+00:00",
    "completed_at": "2026-03-10T10:48:24.892121+00:00",
    "records_added": 52,
    "records_updated": 0,
    "status": "completed",
    "error": null
  },
  {
    "id": 5,
    "engine": "costs",
    "source": "usaspending",
    "started_at": "2026-03-10T10:41:07.696138+00:00",
    "completed_at": "2026-03-10T10:47:31.725494+00:00",
    "records_added": 0,
    "records_updated": 0,
    "status": "completed",
    "error": null
  },
  {
    "id": 4,
    "engine": "costs",
    "source": "hud",
    "started_at": "2026-03-10T10:36:01.053721+00:00",
    "completed_at": "2026-03-10T10:41:07.695828+00:00",
    "records_added": 0,
    "records_updated": 0,
    "status": "completed",
    "error": null
  },
  {
    "id": 3,
    "engine": "costs",
    "source": "cms",
    "started_at": "2026-03-10T10:34:59.306715+00:00",
    "completed_at": "2026-03-10T10:36:01.053373+00:00",
    "records_added": 0,
    "records_updated": 0,
    "status": "completed",
    "error": null
  },
  {
    "id": 2,
    "engine": "legal",
    "source": "federal_register",
    "started_at": "2026-03-10T10:33:55.024833+00:00",
    "completed_at": "2026-03-10T10:34:59.306270+00:00",
    "records_added": 152,
    "records_updated": 8,
    "status": "completed",
    "error": null
  },
  {
    "id": 1,
    "engine": "legal",
    "source": "ecfr",
    "started_at": "2026-03-10T10:33:51.487638+00:00",
    "completed_at": "2026-03-10T10:33:55.024517+00:00",
    "records_added": 4944,
    "records_updated": 29,
    "status": "completed",
    "error": null
  }
]