[
  {
    "id": 7,
    "engine": "parcels",
    "source": "opendataphilly",
    "started_at": "2026-04-01T15:14:14.800679+00:00",
    "completed_at": "2026-04-01T15:16:19.262625+00:00",
    "records_added": 0,
    "records_updated": 0,
    "status": "completed",
    "error": null
  },
  {
    "id": 6,
    "engine": "systems",
    "source": "usaspending",
    "started_at": "2026-04-01T15:13:19.995078+00:00",
    "completed_at": "2026-04-01T15:14:14.800442+00:00",
    "records_added": 52,
    "records_updated": 0,
    "status": "completed",
    "error": null
  },
  {
    "id": 5,
    "engine": "costs",
    "source": "usaspending",
    "started_at": "2026-04-01T15:06:58.763547+00:00",
    "completed_at": "2026-04-01T15:13:19.994683+00:00",
    "records_added": 0,
    "records_updated": 0,
    "status": "completed",
    "error": null
  },
  {
    "id": 4,
    "engine": "costs",
    "source": "hud",
    "started_at": "2026-04-01T15:01:48.185050+00:00",
    "completed_at": "2026-04-01T15:06:58.763071+00:00",
    "records_added": 0,
    "records_updated": 0,
    "status": "completed",
    "error": null
  },
  {
    "id": 3,
    "engine": "costs",
    "source": "cms",
    "started_at": "2026-04-01T15:00:46.241840+00:00",
    "completed_at": "2026-04-01T15:01:48.184630+00:00",
    "records_added": 0,
    "records_updated": 0,
    "status": "completed",
    "error": null
  },
  {
    "id": 2,
    "engine": "legal",
    "source": "federal_register",
    "started_at": "2026-04-01T14:59:37.106730+00:00",
    "completed_at": "2026-04-01T15:00:46.241442+00:00",
    "records_added": 154,
    "records_updated": 6,
    "status": "completed",
    "error": null
  },
  {
    "id": 1,
    "engine": "legal",
    "source": "ecfr",
    "started_at": "2026-04-01T14:59:29.166589+00:00",
    "completed_at": "2026-04-01T14:59:37.106320+00:00",
    "records_added": 4944,
    "records_updated": 29,
    "status": "completed",
    "error": null
  }
]