[
  {
    "id": 7,
    "engine": "parcels",
    "source": "opendataphilly",
    "started_at": "2026-06-19T15:17:14.430989+00:00",
    "completed_at": "2026-06-19T15:19:18.721481+00:00",
    "records_added": 0,
    "records_updated": 0,
    "status": "completed",
    "error": null
  },
  {
    "id": 6,
    "engine": "systems",
    "source": "usaspending",
    "started_at": "2026-06-19T15:16:37.421398+00:00",
    "completed_at": "2026-06-19T15:17:14.430786+00:00",
    "records_added": 52,
    "records_updated": 0,
    "status": "completed",
    "error": null
  },
  {
    "id": 5,
    "engine": "costs",
    "source": "usaspending",
    "started_at": "2026-06-19T15:10:08.609147+00:00",
    "completed_at": "2026-06-19T15:16:37.420963+00:00",
    "records_added": 0,
    "records_updated": 0,
    "status": "completed",
    "error": null
  },
  {
    "id": 4,
    "engine": "costs",
    "source": "hud",
    "started_at": "2026-06-19T15:05:00.438235+00:00",
    "completed_at": "2026-06-19T15:10:08.608722+00:00",
    "records_added": 0,
    "records_updated": 0,
    "status": "completed",
    "error": null
  },
  {
    "id": 3,
    "engine": "costs",
    "source": "cms",
    "started_at": "2026-06-19T15:03:59.238946+00:00",
    "completed_at": "2026-06-19T15:05:00.437859+00:00",
    "records_added": 0,
    "records_updated": 0,
    "status": "completed",
    "error": null
  },
  {
    "id": 2,
    "engine": "legal",
    "source": "federal_register",
    "started_at": "2026-06-19T15:02:56.157905+00:00",
    "completed_at": "2026-06-19T15:03:59.238565+00:00",
    "records_added": 157,
    "records_updated": 3,
    "status": "completed",
    "error": null
  },
  {
    "id": 1,
    "engine": "legal",
    "source": "ecfr",
    "started_at": "2026-06-19T15:02:53.817689+00:00",
    "completed_at": "2026-06-19T15:02:56.157579+00:00",
    "records_added": 4927,
    "records_updated": 29,
    "status": "completed",
    "error": null
  }
]