[
  {
    "id": 7,
    "engine": "parcels",
    "source": "opendataphilly",
    "started_at": "2026-04-02T04:40:39.788410+00:00",
    "completed_at": "2026-04-02T04:42:43.005629+00:00",
    "records_added": 0,
    "records_updated": 0,
    "status": "completed",
    "error": null
  },
  {
    "id": 6,
    "engine": "systems",
    "source": "usaspending",
    "started_at": "2026-04-02T04:39:38.011999+00:00",
    "completed_at": "2026-04-02T04:40:39.788227+00:00",
    "records_added": 52,
    "records_updated": 0,
    "status": "completed",
    "error": null
  },
  {
    "id": 5,
    "engine": "costs",
    "source": "usaspending",
    "started_at": "2026-04-02T04:33:14.573294+00:00",
    "completed_at": "2026-04-02T04:39:38.011626+00:00",
    "records_added": 0,
    "records_updated": 0,
    "status": "completed",
    "error": null
  },
  {
    "id": 4,
    "engine": "costs",
    "source": "hud",
    "started_at": "2026-04-02T04:28:07.991552+00:00",
    "completed_at": "2026-04-02T04:33:14.572875+00:00",
    "records_added": 0,
    "records_updated": 0,
    "status": "completed",
    "error": null
  },
  {
    "id": 3,
    "engine": "costs",
    "source": "cms",
    "started_at": "2026-04-02T04:27:06.234755+00:00",
    "completed_at": "2026-04-02T04:28:07.991038+00:00",
    "records_added": 0,
    "records_updated": 0,
    "status": "completed",
    "error": null
  },
  {
    "id": 2,
    "engine": "legal",
    "source": "federal_register",
    "started_at": "2026-04-02T04:26:02.183845+00:00",
    "completed_at": "2026-04-02T04:27:06.234344+00:00",
    "records_added": 154,
    "records_updated": 6,
    "status": "completed",
    "error": null
  },
  {
    "id": 1,
    "engine": "legal",
    "source": "ecfr",
    "started_at": "2026-04-02T04:25:58.322134+00:00",
    "completed_at": "2026-04-02T04:26:02.183552+00:00",
    "records_added": 4944,
    "records_updated": 29,
    "status": "completed",
    "error": null
  }
]