[
  {
    "id": 7,
    "engine": "parcels",
    "source": "opendataphilly",
    "started_at": "2026-03-14T04:21:04.569946+00:00",
    "completed_at": "2026-03-14T04:23:09.224463+00:00",
    "records_added": 0,
    "records_updated": 0,
    "status": "completed",
    "error": null
  },
  {
    "id": 6,
    "engine": "systems",
    "source": "usaspending",
    "started_at": "2026-03-14T04:20:13.416442+00:00",
    "completed_at": "2026-03-14T04:21:04.569791+00:00",
    "records_added": 52,
    "records_updated": 0,
    "status": "completed",
    "error": null
  },
  {
    "id": 5,
    "engine": "costs",
    "source": "usaspending",
    "started_at": "2026-03-14T04:13:48.372975+00:00",
    "completed_at": "2026-03-14T04:20:13.416039+00:00",
    "records_added": 0,
    "records_updated": 0,
    "status": "completed",
    "error": null
  },
  {
    "id": 4,
    "engine": "costs",
    "source": "hud",
    "started_at": "2026-03-14T04:08:29.753339+00:00",
    "completed_at": "2026-03-14T04:13:48.372465+00:00",
    "records_added": 0,
    "records_updated": 0,
    "status": "completed",
    "error": null
  },
  {
    "id": 3,
    "engine": "costs",
    "source": "cms",
    "started_at": "2026-03-14T04:07:27.386587+00:00",
    "completed_at": "2026-03-14T04:08:29.752944+00:00",
    "records_added": 0,
    "records_updated": 0,
    "status": "completed",
    "error": null
  },
  {
    "id": 2,
    "engine": "legal",
    "source": "federal_register",
    "started_at": "2026-03-14T04:06:19.985594+00:00",
    "completed_at": "2026-03-14T04:07:27.386159+00:00",
    "records_added": 153,
    "records_updated": 7,
    "status": "completed",
    "error": null
  },
  {
    "id": 1,
    "engine": "legal",
    "source": "ecfr",
    "started_at": "2026-03-14T04:06:14.194491+00:00",
    "completed_at": "2026-03-14T04:06:19.985264+00:00",
    "records_added": 4944,
    "records_updated": 29,
    "status": "completed",
    "error": null
  }
]