[
  {
    "id": 7,
    "engine": "parcels",
    "source": "opendataphilly",
    "started_at": "2026-05-03T10:35:36.559076+00:00",
    "completed_at": "2026-05-03T10:37:44.613690+00:00",
    "records_added": 0,
    "records_updated": 0,
    "status": "completed",
    "error": null
  },
  {
    "id": 6,
    "engine": "systems",
    "source": "usaspending",
    "started_at": "2026-05-03T10:34:49.132764+00:00",
    "completed_at": "2026-05-03T10:35:36.558906+00:00",
    "records_added": 52,
    "records_updated": 0,
    "status": "completed",
    "error": null
  },
  {
    "id": 5,
    "engine": "costs",
    "source": "usaspending",
    "started_at": "2026-05-03T10:28:24.209684+00:00",
    "completed_at": "2026-05-03T10:34:49.132376+00:00",
    "records_added": 0,
    "records_updated": 0,
    "status": "completed",
    "error": null
  },
  {
    "id": 4,
    "engine": "costs",
    "source": "hud",
    "started_at": "2026-05-03T10:23:14.558822+00:00",
    "completed_at": "2026-05-03T10:28:24.209325+00:00",
    "records_added": 0,
    "records_updated": 0,
    "status": "completed",
    "error": null
  },
  {
    "id": 3,
    "engine": "costs",
    "source": "cms",
    "started_at": "2026-05-03T10:22:12.546101+00:00",
    "completed_at": "2026-05-03T10:23:14.558461+00:00",
    "records_added": 0,
    "records_updated": 0,
    "status": "completed",
    "error": null
  },
  {
    "id": 2,
    "engine": "legal",
    "source": "federal_register",
    "started_at": "2026-05-03T10:21:07.847949+00:00",
    "completed_at": "2026-05-03T10:22:12.545765+00:00",
    "records_added": 158,
    "records_updated": 2,
    "status": "completed",
    "error": null
  },
  {
    "id": 1,
    "engine": "legal",
    "source": "ecfr",
    "started_at": "2026-05-03T10:21:04.225755+00:00",
    "completed_at": "2026-05-03T10:21:07.847608+00:00",
    "records_added": 4926,
    "records_updated": 29,
    "status": "completed",
    "error": null
  }
]