[
  {
    "id": 7,
    "engine": "parcels",
    "source": "opendataphilly",
    "started_at": "2026-03-14T14:37:43.631677+00:00",
    "completed_at": "2026-03-14T14:39:46.924562+00:00",
    "records_added": 0,
    "records_updated": 0,
    "status": "completed",
    "error": null
  },
  {
    "id": 6,
    "engine": "systems",
    "source": "usaspending",
    "started_at": "2026-03-14T14:37:01.617412+00:00",
    "completed_at": "2026-03-14T14:37:43.631498+00:00",
    "records_added": 52,
    "records_updated": 0,
    "status": "completed",
    "error": null
  },
  {
    "id": 5,
    "engine": "costs",
    "source": "usaspending",
    "started_at": "2026-03-14T14:30:36.451508+00:00",
    "completed_at": "2026-03-14T14:37:01.617079+00:00",
    "records_added": 0,
    "records_updated": 0,
    "status": "completed",
    "error": null
  },
  {
    "id": 4,
    "engine": "costs",
    "source": "hud",
    "started_at": "2026-03-14T14:25:25.713050+00:00",
    "completed_at": "2026-03-14T14:30:36.451069+00:00",
    "records_added": 0,
    "records_updated": 0,
    "status": "completed",
    "error": null
  },
  {
    "id": 3,
    "engine": "costs",
    "source": "cms",
    "started_at": "2026-03-14T14:24:23.956653+00:00",
    "completed_at": "2026-03-14T14:25:25.712671+00:00",
    "records_added": 0,
    "records_updated": 0,
    "status": "completed",
    "error": null
  },
  {
    "id": 2,
    "engine": "legal",
    "source": "federal_register",
    "started_at": "2026-03-14T14:23:19.662242+00:00",
    "completed_at": "2026-03-14T14:24:23.956181+00:00",
    "records_added": 153,
    "records_updated": 7,
    "status": "completed",
    "error": null
  },
  {
    "id": 1,
    "engine": "legal",
    "source": "ecfr",
    "started_at": "2026-03-14T14:23:16.221315+00:00",
    "completed_at": "2026-03-14T14:23:19.661921+00:00",
    "records_added": 4944,
    "records_updated": 29,
    "status": "completed",
    "error": null
  }
]