[
  {
    "id": 7,
    "engine": "parcels",
    "source": "opendataphilly",
    "started_at": "2026-04-19T05:02:30.715396+00:00",
    "completed_at": "2026-04-19T05:04:35.499917+00:00",
    "records_added": 0,
    "records_updated": 0,
    "status": "completed",
    "error": null
  },
  {
    "id": 6,
    "engine": "systems",
    "source": "usaspending",
    "started_at": "2026-04-19T05:01:36.980187+00:00",
    "completed_at": "2026-04-19T05:02:30.715255+00:00",
    "records_added": 52,
    "records_updated": 0,
    "status": "completed",
    "error": null
  },
  {
    "id": 5,
    "engine": "costs",
    "source": "usaspending",
    "started_at": "2026-04-19T04:55:09.381183+00:00",
    "completed_at": "2026-04-19T05:01:36.979853+00:00",
    "records_added": 0,
    "records_updated": 0,
    "status": "completed",
    "error": null
  },
  {
    "id": 4,
    "engine": "costs",
    "source": "hud",
    "started_at": "2026-04-19T04:49:56.149174+00:00",
    "completed_at": "2026-04-19T04:55:09.380841+00:00",
    "records_added": 0,
    "records_updated": 0,
    "status": "completed",
    "error": null
  },
  {
    "id": 3,
    "engine": "costs",
    "source": "cms",
    "started_at": "2026-04-19T04:48:53.489788+00:00",
    "completed_at": "2026-04-19T04:49:56.148842+00:00",
    "records_added": 0,
    "records_updated": 0,
    "status": "completed",
    "error": null
  },
  {
    "id": 2,
    "engine": "legal",
    "source": "federal_register",
    "started_at": "2026-04-19T04:47:45.889534+00:00",
    "completed_at": "2026-04-19T04:48:53.489261+00:00",
    "records_added": 156,
    "records_updated": 4,
    "status": "completed",
    "error": null
  },
  {
    "id": 1,
    "engine": "legal",
    "source": "ecfr",
    "started_at": "2026-04-19T04:47:40.067547+00:00",
    "completed_at": "2026-04-19T04:47:45.889279+00:00",
    "records_added": 4926,
    "records_updated": 29,
    "status": "completed",
    "error": null
  }
]