[
  {
    "id": 7,
    "engine": "parcels",
    "source": "opendataphilly",
    "started_at": "2026-06-16T08:10:36.549716+00:00",
    "completed_at": "2026-06-16T08:12:40.432739+00:00",
    "records_added": 0,
    "records_updated": 0,
    "status": "completed",
    "error": null
  },
  {
    "id": 6,
    "engine": "systems",
    "source": "usaspending",
    "started_at": "2026-06-16T08:09:43.353198+00:00",
    "completed_at": "2026-06-16T08:10:36.549494+00:00",
    "records_added": 52,
    "records_updated": 0,
    "status": "completed",
    "error": null
  },
  {
    "id": 5,
    "engine": "costs",
    "source": "usaspending",
    "started_at": "2026-06-16T08:03:17.783597+00:00",
    "completed_at": "2026-06-16T08:09:43.352807+00:00",
    "records_added": 0,
    "records_updated": 0,
    "status": "completed",
    "error": null
  },
  {
    "id": 4,
    "engine": "costs",
    "source": "hud",
    "started_at": "2026-06-16T07:58:04.976844+00:00",
    "completed_at": "2026-06-16T08:03:17.783107+00:00",
    "records_added": 0,
    "records_updated": 0,
    "status": "completed",
    "error": null
  },
  {
    "id": 3,
    "engine": "costs",
    "source": "cms",
    "started_at": "2026-06-16T07:57:01.279968+00:00",
    "completed_at": "2026-06-16T07:58:04.976495+00:00",
    "records_added": 0,
    "records_updated": 0,
    "status": "completed",
    "error": null
  },
  {
    "id": 2,
    "engine": "legal",
    "source": "federal_register",
    "started_at": "2026-06-16T07:55:58.171351+00:00",
    "completed_at": "2026-06-16T07:57:01.279633+00:00",
    "records_added": 157,
    "records_updated": 3,
    "status": "completed",
    "error": null
  },
  {
    "id": 1,
    "engine": "legal",
    "source": "ecfr",
    "started_at": "2026-06-16T07:55:56.032240+00:00",
    "completed_at": "2026-06-16T07:55:58.171065+00:00",
    "records_added": 4927,
    "records_updated": 29,
    "status": "completed",
    "error": null
  }
]