[
  {
    "id": 7,
    "engine": "parcels",
    "source": "opendataphilly",
    "started_at": "2026-03-06T06:54:55.922666+00:00",
    "completed_at": "2026-03-06T06:57:01.595277+00:00",
    "records_added": 0,
    "records_updated": 0,
    "status": "completed",
    "error": null
  },
  {
    "id": 6,
    "engine": "systems",
    "source": "usaspending",
    "started_at": "2026-03-06T06:54:17.912625+00:00",
    "completed_at": "2026-03-06T06:54:55.922501+00:00",
    "records_added": 52,
    "records_updated": 0,
    "status": "completed",
    "error": null
  },
  {
    "id": 5,
    "engine": "costs",
    "source": "usaspending",
    "started_at": "2026-03-06T06:47:56.343038+00:00",
    "completed_at": "2026-03-06T06:54:17.912235+00:00",
    "records_added": 0,
    "records_updated": 0,
    "status": "completed",
    "error": null
  },
  {
    "id": 4,
    "engine": "costs",
    "source": "hud",
    "started_at": "2026-03-06T06:42:43.109988+00:00",
    "completed_at": "2026-03-06T06:47:56.342621+00:00",
    "records_added": 0,
    "records_updated": 0,
    "status": "completed",
    "error": null
  },
  {
    "id": 3,
    "engine": "costs",
    "source": "cms",
    "started_at": "2026-03-06T06:41:40.730722+00:00",
    "completed_at": "2026-03-06T06:42:43.109562+00:00",
    "records_added": 0,
    "records_updated": 0,
    "status": "completed",
    "error": null
  },
  {
    "id": 2,
    "engine": "legal",
    "source": "federal_register",
    "started_at": "2026-03-06T06:40:33.255464+00:00",
    "completed_at": "2026-03-06T06:41:40.730072+00:00",
    "records_added": 152,
    "records_updated": 8,
    "status": "completed",
    "error": null
  },
  {
    "id": 1,
    "engine": "legal",
    "source": "ecfr",
    "started_at": "2026-03-06T06:40:25.779357+00:00",
    "completed_at": "2026-03-06T06:40:33.255157+00:00",
    "records_added": 4944,
    "records_updated": 29,
    "status": "completed",
    "error": null
  }
]