[
  {
    "id": 7,
    "engine": "parcels",
    "source": "opendataphilly",
    "started_at": "2026-06-10T17:09:37.264032+00:00",
    "completed_at": "2026-06-10T17:11:41.166347+00:00",
    "records_added": 0,
    "records_updated": 0,
    "status": "completed",
    "error": null
  },
  {
    "id": 6,
    "engine": "systems",
    "source": "usaspending",
    "started_at": "2026-06-10T17:08:43.364169+00:00",
    "completed_at": "2026-06-10T17:09:37.263856+00:00",
    "records_added": 52,
    "records_updated": 0,
    "status": "completed",
    "error": null
  },
  {
    "id": 5,
    "engine": "costs",
    "source": "usaspending",
    "started_at": "2026-06-10T17:02:18.728389+00:00",
    "completed_at": "2026-06-10T17:08:43.363806+00:00",
    "records_added": 0,
    "records_updated": 0,
    "status": "completed",
    "error": null
  },
  {
    "id": 4,
    "engine": "costs",
    "source": "hud",
    "started_at": "2026-06-10T16:57:02.862946+00:00",
    "completed_at": "2026-06-10T17:02:18.728005+00:00",
    "records_added": 0,
    "records_updated": 0,
    "status": "completed",
    "error": null
  },
  {
    "id": 3,
    "engine": "costs",
    "source": "cms",
    "started_at": "2026-06-10T16:55:59.991511+00:00",
    "completed_at": "2026-06-10T16:57:02.862576+00:00",
    "records_added": 0,
    "records_updated": 0,
    "status": "completed",
    "error": null
  },
  {
    "id": 2,
    "engine": "legal",
    "source": "federal_register",
    "started_at": "2026-06-10T16:54:55.236509+00:00",
    "completed_at": "2026-06-10T16:55:59.991137+00:00",
    "records_added": 157,
    "records_updated": 3,
    "status": "completed",
    "error": null
  },
  {
    "id": 1,
    "engine": "legal",
    "source": "ecfr",
    "started_at": "2026-06-10T16:54:51.880465+00:00",
    "completed_at": "2026-06-10T16:54:55.236151+00:00",
    "records_added": 4927,
    "records_updated": 29,
    "status": "completed",
    "error": null
  }
]