[
  {
    "id": 7,
    "engine": "parcels",
    "source": "opendataphilly",
    "started_at": "2026-06-14T07:49:47.692329+00:00",
    "completed_at": "2026-06-14T07:51:52.963669+00:00",
    "records_added": 0,
    "records_updated": 0,
    "status": "completed",
    "error": null
  },
  {
    "id": 6,
    "engine": "systems",
    "source": "usaspending",
    "started_at": "2026-06-14T07:48:56.198631+00:00",
    "completed_at": "2026-06-14T07:49:47.692128+00:00",
    "records_added": 52,
    "records_updated": 0,
    "status": "completed",
    "error": null
  },
  {
    "id": 5,
    "engine": "costs",
    "source": "usaspending",
    "started_at": "2026-06-14T07:42:38.690654+00:00",
    "completed_at": "2026-06-14T07:48:56.198225+00:00",
    "records_added": 0,
    "records_updated": 0,
    "status": "completed",
    "error": null
  },
  {
    "id": 4,
    "engine": "costs",
    "source": "hud",
    "started_at": "2026-06-14T07:37:21.681107+00:00",
    "completed_at": "2026-06-14T07:42:38.690292+00:00",
    "records_added": 0,
    "records_updated": 0,
    "status": "completed",
    "error": null
  },
  {
    "id": 3,
    "engine": "costs",
    "source": "cms",
    "started_at": "2026-06-14T07:36:19.542727+00:00",
    "completed_at": "2026-06-14T07:37:21.680690+00:00",
    "records_added": 0,
    "records_updated": 0,
    "status": "completed",
    "error": null
  },
  {
    "id": 2,
    "engine": "legal",
    "source": "federal_register",
    "started_at": "2026-06-14T07:35:12.979434+00:00",
    "completed_at": "2026-06-14T07:36:19.542344+00:00",
    "records_added": 157,
    "records_updated": 3,
    "status": "completed",
    "error": null
  },
  {
    "id": 1,
    "engine": "legal",
    "source": "ecfr",
    "started_at": "2026-06-14T07:35:08.790660+00:00",
    "completed_at": "2026-06-14T07:35:12.979151+00:00",
    "records_added": 4927,
    "records_updated": 29,
    "status": "completed",
    "error": null
  }
]