{
  "category": "housing",
  "types": 6,
  "total_characters": 94,
  "entries": [
    {
      "type": "housing_insecure",
      "category": "housing",
      "layers": [
        5,
        3
      ],
      "description": "Unstable housing, at risk of loss",
      "character_count": 48,
      "real_count": 33,
      "fictional_count": 15,
      "example_characters": [
        {
          "name": "Arleen Belle",
          "source_work": "Evicted: Poverty and Profit in the American City",
          "real_or_fictional": "real"
        },
        {
          "name": "Scott Bunker",
          "source_work": "Evicted: Poverty and Profit in the American City",
          "real_or_fictional": "real"
        },
        {
          "name": "Lamar",
          "source_work": "Evicted: Poverty and Profit in the American City",
          "real_or_fictional": "real"
        },
        {
          "name": "Jessica",
          "source_work": "Random Family: Love, Drugs, Trouble, and Coming of Age in the Bronx",
          "real_or_fictional": "real"
        },
        {
          "name": "Coco",
          "source_work": "Random Family: Love, Drugs, Trouble, and Coming of Age in the Bronx",
          "real_or_fictional": "real"
        },
        {
          "name": "Barbara Ehrenreich (as worker)",
          "source_work": "Nickel and Dimed: On (Not) Getting By in America",
          "real_or_fictional": "real"
        },
        {
          "name": "Abdul Husain",
          "source_work": "Behind the Beautiful Forevers: Life, Death, and Hope in a Mumbai Undercity",
          "real_or_fictional": "real"
        },
        {
          "name": "Asha Waghekar",
          "source_work": "Behind the Beautiful Forevers: Life, Death, and Hope in a Mumbai Undercity",
          "real_or_fictional": "real"
        },
        {
          "name": "Jennifer Hernandez",
          "source_work": "$2.00 a Day: Living on Almost Nothing in America",
          "real_or_fictional": "real"
        },
        {
          "name": "Rae McCormick",
          "source_work": "$2.00 a Day: Living on Almost Nothing in America",
          "real_or_fictional": "real"
        }
      ],
      "discovered_at": "2026-02-26T21:44:38.904Z",
      "discovered_from": "built-in taxonomy"
    },
    {
      "type": "homeless",
      "category": "housing",
      "layers": [
        5,
        3,
        8
      ],
      "description": "Without stable housing",
      "character_count": 25,
      "real_count": 13,
      "fictional_count": 12,
      "example_characters": [
        {
          "name": "Crystal Mayberry",
          "source_work": "Evicted: Poverty and Profit in the American City",
          "real_or_fictional": "real"
        },
        {
          "name": "Dasani Coates",
          "source_work": "Invisible Child: Poverty, Survival & Hope in an American City",
          "real_or_fictional": "real"
        },
        {
          "name": "Chanel Sykes",
          "source_work": "Invisible Child: Poverty, Survival & Hope in an American City",
          "real_or_fictional": "real"
        },
        {
          "name": "Jeannette Walls",
          "source_work": "The Glass Castle",
          "real_or_fictional": "real"
        },
        {
          "name": "David Wojnarowicz",
          "source_work": "In the Shadow of the American Dream: The Diaries of David Wojnarowicz",
          "real_or_fictional": "real"
        },
        {
          "name": "The Afghanistan Veterans",
          "source_work": "The Afghanistan Papers (Washington Post)",
          "real_or_fictional": "real"
        },
        {
          "name": "The Auburn Shelter Families",
          "source_work": "Invisible Child (NYT Series)",
          "real_or_fictional": "real"
        },
        {
          "name": "Matthew Charles",
          "source_work": "Senate Judiciary Committee Testimony on First Step Act",
          "real_or_fictional": "real"
        },
        {
          "name": "The Frequent Flyer (Emergency Medicine Literature)",
          "source_work": "Super-Utilizers in Emergency Medicine (Annals of Emergency Medicine)",
          "real_or_fictional": "real"
        },
        {
          "name": "Dynamite Garland (Hobo)",
          "source_work": "Hard Times: An Oral History of the Great Depression",
          "real_or_fictional": "real"
        }
      ],
      "discovered_at": "2026-02-26T21:44:38.904Z",
      "discovered_from": "built-in taxonomy"
    },
    {
      "type": "displaced",
      "category": "housing",
      "layers": [
        5,
        8,
        9
      ],
      "description": "Displaced from home by force, disaster, or policy",
      "character_count": 13,
      "real_count": 7,
      "fictional_count": 6,
      "example_characters": [
        {
          "name": "Ida Mae Brandon Gladney",
          "source_work": "The Warmth of Other Suns: The Epic Story of America's Great Migration",
          "real_or_fictional": "real"
        },
        {
          "name": "George Swanson Starling",
          "source_work": "The Warmth of Other Suns: The Epic Story of America's Great Migration",
          "real_or_fictional": "real"
        },
        {
          "name": "Robert Joseph Pershing Foster",
          "source_work": "The Warmth of Other Suns: The Epic Story of America's Great Migration",
          "real_or_fictional": "real"
        },
        {
          "name": "George Takei (as child)",
          "source_work": "They Called Us Enemy",
          "real_or_fictional": "real"
        },
        {
          "name": "Clyde Ross",
          "source_work": "The Case for Reparations (The Atlantic) / The 1619 Project",
          "real_or_fictional": "real"
        },
        {
          "name": "Tom Joad",
          "source_work": "The Grapes of Wrath",
          "real_or_fictional": "fictional"
        },
        {
          "name": "Ellie (The Last of Us)",
          "source_work": "The Last of Us (Video Game)",
          "real_or_fictional": "fictional"
        },
        {
          "name": "Lee Everett",
          "source_work": "The Walking Dead (Telltale Game)",
          "real_or_fictional": "fictional"
        },
        {
          "name": "Odysseus",
          "source_work": "The Odyssey",
          "real_or_fictional": "fictional"
        },
        {
          "name": "Sita",
          "source_work": "The Ramayana",
          "real_or_fictional": "fictional"
        }
      ],
      "discovered_at": "2026-02-26T21:44:38.904Z",
      "discovered_from": "built-in taxonomy"
    },
    {
      "type": "evicted",
      "category": "housing",
      "layers": [
        5,
        1,
        3
      ],
      "description": "Forcibly removed from housing",
      "character_count": 4,
      "real_count": 4,
      "fictional_count": 0,
      "example_characters": [
        {
          "name": "Arleen Belle",
          "source_work": "Evicted: Poverty and Profit in the American City",
          "real_or_fictional": "real"
        },
        {
          "name": "Crystal Mayberry",
          "source_work": "Evicted: Poverty and Profit in the American City",
          "real_or_fictional": "real"
        },
        {
          "name": "Scott Bunker",
          "source_work": "Evicted: Poverty and Profit in the American City",
          "real_or_fictional": "real"
        },
        {
          "name": "Lamar",
          "source_work": "Evicted: Poverty and Profit in the American City",
          "real_or_fictional": "real"
        }
      ],
      "discovered_at": "2026-02-26T21:44:38.904Z",
      "discovered_from": "built-in taxonomy"
    },
    {
      "type": "shelter",
      "category": "housing",
      "layers": [
        5,
        2
      ],
      "description": "Living in emergency shelter",
      "character_count": 3,
      "real_count": 3,
      "fictional_count": 0,
      "example_characters": [
        {
          "name": "Dasani Coates",
          "source_work": "Invisible Child: Poverty, Survival & Hope in an American City",
          "real_or_fictional": "real"
        },
        {
          "name": "Chanel Sykes",
          "source_work": "Invisible Child: Poverty, Survival & Hope in an American City",
          "real_or_fictional": "real"
        },
        {
          "name": "The Auburn Shelter Families",
          "source_work": "Invisible Child (NYT Series)",
          "real_or_fictional": "real"
        }
      ],
      "discovered_at": "2026-02-26T21:44:38.904Z",
      "discovered_from": "built-in taxonomy"
    },
    {
      "type": "institutionalized",
      "category": "housing",
      "layers": [
        5,
        1,
        10
      ],
      "description": "Living in an institution (nursing home, group home, etc.)",
      "character_count": 1,
      "real_count": 0,
      "fictional_count": 1,
      "example_characters": [
        {
          "name": "Oliver Twist",
          "source_work": "Oliver Twist",
          "real_or_fictional": "fictional"
        }
      ],
      "discovered_at": "2026-02-26T21:44:38.904Z",
      "discovered_from": "built-in taxonomy"
    }
  ]
}
